{
  "notifications": [
    {
      "_id": "69e3d8d47ceeabd32451d2e9",
      "recipient": "69dc95635bcfc7742725390a",
      "actor": "69de030e1b0c613b1907833e",
      "type": "styled_outfit_shared",
      "message": "@Ramy, a new styled outfit was created for you: Look for Ramy",
      "outfit": "69e3d8d47ceeabd32451d2e5",
      "communityPost": "69e3d8d47ceeabd32451d2e7",
      "readAt": null,
      "metadata": {
        "stylistUserId": "69de030e1b0c613b1907833e",
        "targetUserId": "69dc95635bcfc7742725390a",
        "outfitName": "Look for Ramy"
      },
      "createdAt": "2026-04-18T19:17:40.611Z",
      "updatedAt": "2026-04-18T19:17:40.611Z",
      "__v": 0
    },
    {
      "_id": "69e3d9e27ceeabd32451d324",
      "recipient": "69dc95635bcfc7742725390a",
      "actor": "69de030e1b0c613b1907833e",
      "type": "styled_outfit_shared",
      "message": "@Ramy, a new styled outfit was created for you: Look for Ramy",
      "outfit": "69e3d9e27ceeabd32451d320",
      "communityPost": "69e3d9e27ceeabd32451d322",
      "readAt": null,
      "metadata": {
        "stylistUserId": "69de030e1b0c613b1907833e",
        "targetUserId": "69dc95635bcfc7742725390a",
        "outfitName": "Look for Ramy"
      },
      "createdAt": "2026-04-18T19:22:10.164Z",
      "updatedAt": "2026-04-18T19:22:10.164Z",
      "__v": 0
    },
    {
      "_id": "69e3dbbb7ceeabd32451d357",
      "recipient": "69dc95635bcfc7742725390a",
      "actor": "69de030e1b0c613b1907833e",
      "type": "styled_outfit_shared",
      "message": "@Ramy, a new styled outfit was created for you: Ramy Look",
      "outfit": "69e3dbbb7ceeabd32451d353",
      "communityPost": "69e3dbbb7ceeabd32451d355",
      "readAt": null,
      "metadata": {
        "stylistUserId": "69de030e1b0c613b1907833e",
        "targetUserId": "69dc95635bcfc7742725390a",
        "outfitName": "Ramy Look"
      },
      "createdAt": "2026-04-18T19:30:03.160Z",
      "updatedAt": "2026-04-18T19:30:03.160Z",
      "__v": 0
    }
  ],
  "outfits": [
    {
      "_id": "69dcac5c805be30ff653ec8d",
      "name": "Randomize Outfit",
      "garments": [
        "69dca76f805be30ff653eb4a",
        "69dcabe5805be30ff653ec3a",
        "69dca9fd805be30ff653ebfa",
        "69dca81f805be30ff653eba2"
      ],
      "previewImage": "https://res.cloudinary.com/dazn6zthy/image/upload/digital-wardrobe/image-1776068460450-bb2da0cf8b1f3ab1.png",
      "previewImageMetadata": null,
      "isLookbook": false,
      "owner": "69dc95635bcfc7742725390a",
      "createdAt": "2026-04-13T08:42:04.441Z",
      "updatedAt": "2026-04-13T09:46:38.977Z",
      "__v": 0
    },
    {
      "_id": "69dcac6d805be30ff653ec95",
      "name": "Randomize Outfit",
      "garments": [
        "69dc9fe8805be30ff653ea4c",
        "69dcac0d805be30ff653ec3f",
        "69dcaa75805be30ff653ec04",
        "69dca87f805be30ff653ebd4"
      ],
      "previewImage": "https://res.cloudinary.com/dazn6zthy/image/upload/digital-wardrobe/image-1776066547951-3068543baedaee7e.png",
      "previewImageMetadata": null,
      "isLookbook": false,
      "owner": "69dc95635bcfc7742725390a",
      "createdAt": "2026-04-13T08:42:21.928Z",
      "updatedAt": "2026-04-13T09:46:39.033Z",
      "__v": 0
    },
    {
      "_id": "69dcac79805be30ff653ec9d",
      "name": "Randomize Outfit",
      "garments": [
        "69dcaa75805be30ff653ec04",
        "69dca9c1805be30ff653ebe3",
        "69dca76f805be30ff653eb4a",
        "69dca87f805be30ff653ebd4"
      ],
      "previewImage": "https://res.cloudinary.com/dazn6zthy/image/upload/digital-wardrobe/image-1776068460450-bb2da0cf8b1f3ab1.png",
      "previewImageMetadata": null,
      "isLookbook": false,
      "owner": "69dc95635bcfc7742725390a",
      "createdAt": "2026-04-13T08:42:33.424Z",
      "updatedAt": "2026-04-13T09:46:39.088Z",
      "__v": 0
    },
    {
      "_id": "69dcac89805be30ff653eca5",
      "name": "Randomize Outfit",
      "garments": [
        "69dca254805be30ff653eaad",
        "69dcaa60805be30ff653ebff",
        "69dcabe5805be30ff653ec3a",
        "69dcab8e805be30ff653ec30"
      ],
      "previewImage": "https://res.cloudinary.com/dazn6zthy/image/upload/digital-wardrobe/image-1776068498995-77c9d5c260f7e2f1.png",
      "previewImageMetadata": null,
      "isLookbook": false,
      "owner": "69dc95635bcfc7742725390a",
      "createdAt": "2026-04-13T08:42:49.218Z",
      "updatedAt": "2026-04-13T09:46:39.144Z",
      "__v": 0
    },
    {
      "_id": "69dcadbc805be30ff653ecef",
      "name": "Randomize Outfit",
      "garments": [
        "69dca254805be30ff653eaad",
        "69dcaa60805be30ff653ebff",
        "69dcabe5805be30ff653ec3a"
      ],
      "previewImage": "https://res.cloudinary.com/dazn6zthy/image/upload/digital-wardrobe/image-1776068498995-77c9d5c260f7e2f1.png",
      "previewImageMetadata": null,
      "isLookbook": false,
      "owner": "69dc95635bcfc7742725390a",
      "createdAt": "2026-04-13T08:47:56.303Z",
      "updatedAt": "2026-04-13T09:46:39.198Z",
      "__v": 0
    },
    {
      "_id": "69dcb3d2cb67d4bc47c7d938",
      "name": "Summer Fits",
      "garments": [
        "69dcac0d805be30ff653ec3f",
        "69dcabe5805be30ff653ec3a",
        "69dca9c1805be30ff653ebe3",
        "69dcaaa8805be30ff653ec21",
        "69dcaadb805be30ff653ec26"
      ],
      "date": "2026-04-13T09:13:54.697Z",
      "previewImage": "https://res.cloudinary.com/dazn6zthy/image/upload/v1776075919/digital-wardrobe/coverImage-1776075917214-1c0a94faafb35bb3.jpg.jpg",
      "previewImageMetadata": {
        "imageUrl": "https://res.cloudinary.com/dazn6zthy/image/upload/v1776075919/digital-wardrobe/coverImage-1776075917214-1c0a94faafb35bb3.jpg.jpg",
        "provider": "cloudinary",
        "publicId": "digital-wardrobe/coverImage-1776075917214-1c0a94faafb35bb3.jpg",
        "secureUrl": "https://res.cloudinary.com/dazn6zthy/image/upload/v1776075919/digital-wardrobe/coverImage-1776075917214-1c0a94faafb35bb3.jpg.jpg",
        "assetId": "f680e02ebb3734ab502ed1fc84921fc0",
        "version": 1776075919,
        "resourceType": "image",
        "format": "jpg",
        "width": 644,
        "height": 644,
        "bytes": 146313,
        "mimeType": "image/jpeg",
        "originalFilename": "lookbook-cover-1776075917980.jpg",
        "uploadedAt": "2026-04-13T10:25:19.082Z"
      },
      "isLookbook": true,
      "owner": "69dc95635bcfc7742725390a",
      "createdAt": "2026-04-13T09:13:54.111Z",
      "updatedAt": "2026-04-13T10:25:19.135Z",
      "__v": 0
    },
    {
      "_id": "69dd783aff61794f49007760",
      "name": "Randomize Outfit",
      "garments": [
        "69dcab9f805be30ff653ec35",
        "69dca915805be30ff653ebd9",
        "69dca9fd805be30ff653ebfa",
        "69dca254805be30ff653eaad"
      ],
      "previewImage": "https://res.cloudinary.com/dazn6zthy/image/upload/v1776075732/digital-wardrobe/image-1776075730701-773a2e449cee3afb.png.png",
      "previewImageMetadata": null,
      "isLookbook": false,
      "owner": "69dc95635bcfc7742725390a",
      "createdAt": "2026-04-13T23:11:54.544Z",
      "updatedAt": "2026-04-13T23:11:54.544Z",
      "__v": 0
    },
    {
      "_id": "69dd783fff61794f49007763",
      "name": "Randomize Outfit",
      "garments": [
        "69dcab9f805be30ff653ec35",
        "69dca915805be30ff653ebd9",
        "69dca9fd805be30ff653ebfa",
        "69dca254805be30ff653eaad"
      ],
      "date": "2026-04-12T00:00:00.000Z",
      "previewImage": "https://res.cloudinary.com/dazn6zthy/image/upload/v1776075732/digital-wardrobe/image-1776075730701-773a2e449cee3afb.png.png",
      "previewImageMetadata": null,
      "isLookbook": false,
      "owner": "69dc95635bcfc7742725390a",
      "createdAt": "2026-04-13T23:11:59.377Z",
      "updatedAt": "2026-04-13T23:11:59.377Z",
      "__v": 0
    },
    {
      "_id": "69dd78beff61794f49007770",
      "name": "Randomize Outfit",
      "garments": [
        "69dca9c1805be30ff653ebe3",
        "69dca9fd805be30ff653ebfa",
        "69dca81f805be30ff653eba2"
      ],
      "previewImage": "https://res.cloudinary.com/dazn6zthy/image/upload/v1776076000/digital-wardrobe/image-1776075997597-7ee6a2b27f9d0339.png.png",
      "previewImageMetadata": null,
      "isLookbook": false,
      "owner": "69dc95635bcfc7742725390a",
      "createdAt": "2026-04-13T23:14:06.506Z",
      "updatedAt": "2026-04-13T23:14:06.506Z",
      "__v": 0
    },
    {
      "_id": "69dd78e1ff61794f49007775",
      "name": "Randomize Outfit",
      "garments": [
        "69dca9c1805be30ff653ebe3",
        "69dcaa60805be30ff653ebff",
        "69dca81f805be30ff653eba2"
      ],
      "date": "2026-04-13T00:00:00.000Z",
      "previewImage": "https://res.cloudinary.com/dazn6zthy/image/upload/v1776076000/digital-wardrobe/image-1776075997597-7ee6a2b27f9d0339.png.png",
      "previewImageMetadata": null,
      "isLookbook": false,
      "owner": "69dc95635bcfc7742725390a",
      "createdAt": "2026-04-13T23:14:41.312Z",
      "updatedAt": "2026-04-13T23:14:41.312Z",
      "__v": 0
    },
    {
      "_id": "69dd793aff61794f490077cc",
      "name": "Randomize Outfit",
      "garments": [
        "69dc9fe8805be30ff653ea4c",
        "69dcac0d805be30ff653ec3f",
        "69dcaa75805be30ff653ec04",
        "69dca87f805be30ff653ebd4"
      ],
      "date": "2026-04-17T00:00:00.000Z",
      "previewImage": "https://res.cloudinary.com/dazn6zthy/image/upload/v1776075683/digital-wardrobe/image-1776075681042-5c9a5edfc1fb1027.png.png",
      "previewImageMetadata": null,
      "isLookbook": false,
      "owner": "69dc95635bcfc7742725390a",
      "createdAt": "2026-04-13T23:16:10.351Z",
      "updatedAt": "2026-04-13T23:16:10.351Z",
      "__v": 0
    },
    {
      "_id": "69dd7c44a1f15d11047d1b26",
      "name": "Date Night",
      "garments": [
        "69dc9fe8805be30ff653ea4c",
        "69dca81f805be30ff653eba2",
        "69dca939805be30ff653ebde",
        "69dcaa60805be30ff653ebff",
        "69dcaa75805be30ff653ec04"
      ],
      "date": "2026-04-13T23:29:09.412Z",
      "previewImage": "https://res.cloudinary.com/dazn6zthy/image/upload/v1776075683/digital-wardrobe/image-1776075681042-5c9a5edfc1fb1027.png.png",
      "previewImageMetadata": null,
      "isLookbook": true,
      "owner": "69dc95635bcfc7742725390a",
      "createdAt": "2026-04-13T23:29:08.778Z",
      "updatedAt": "2026-04-13T23:29:08.778Z",
      "__v": 0
    },
    {
      "_id": "69dd866a035f6b5e0442ed89",
      "name": "Randomize Outfit",
      "garments": [
        "69dcabe5805be30ff653ec3a",
        "69dcaa75805be30ff653ec04",
        "69dca254805be30ff653eaad"
      ],
      "date": "2026-04-06T00:00:00.000Z",
      "previewImage": "https://res.cloudinary.com/dazn6zthy/image/upload/v1776075732/digital-wardrobe/image-1776075730701-773a2e449cee3afb.png.png",
      "previewImageMetadata": null,
      "isLookbook": false,
      "owner": "69dc95635bcfc7742725390a",
      "createdAt": "2026-04-14T00:12:26.301Z",
      "updatedAt": "2026-04-14T00:12:26.301Z",
      "__v": 0
    },
    {
      "_id": "69ddf51debe357f4bac8d240",
      "name": "Randomize Outfit",
      "garments": [
        "69dcaa60805be30ff653ebff",
        "69dca939805be30ff653ebde",
        "69dca87f805be30ff653ebd4"
      ],
      "date": "2026-04-15T00:00:00.000Z",
      "previewImage": "https://res.cloudinary.com/dazn6zthy/image/upload/v1776076000/digital-wardrobe/image-1776075997597-7ee6a2b27f9d0339.png.png",
      "previewImageMetadata": null,
      "isLookbook": false,
      "owner": "69dc95635bcfc7742725390a",
      "createdAt": "2026-04-14T08:04:45.201Z",
      "updatedAt": "2026-04-14T09:01:04.811Z",
      "__v": 1
    },
    {
      "_id": "69de002febe357f4bac8d259",
      "name": "Randomize Outfit",
      "garments": [
        "69dcac0d805be30ff653ec3f",
        "69dcaa60805be30ff653ebff",
        "69dca87f805be30ff653ebd4"
      ],
      "previewImage": "https://res.cloudinary.com/dazn6zthy/image/upload/v1776075556/digital-wardrobe/image-1776075553428-7887ea20213d6179.png.png",
      "previewImageMetadata": null,
      "isLookbook": false,
      "owner": "69dc95635bcfc7742725390a",
      "createdAt": "2026-04-14T08:51:59.948Z",
      "updatedAt": "2026-04-14T08:51:59.948Z",
      "__v": 0
    },
    {
      "_id": "69e3d8d47ceeabd32451d2e5",
      "name": "Look for Ramy",
      "garments": [
        "69dd86fc035f6b5e0442edd2",
        "69dd8875035f6b5e0442ee23",
        "69e2bf58541a1209ba5f88a8",
        "69e2bfb8541a1209ba5f88da"
      ],
      "previewImage": "https://res.cloudinary.com/dazn6zthy/image/upload/v1776125692/digital-wardrobe/image-1776125690634-4ea8935e504a2b90.png.png",
      "previewImageMetadata": null,
      "isLookbook": false,
      "styledFor": "69dc95635bcfc7742725390a",
      "styleNote": "",
      "isSharedWithStyledUser": true,
      "owner": "69de030e1b0c613b1907833e",
      "createdAt": "2026-04-18T19:17:40.460Z",
      "updatedAt": "2026-04-18T19:17:40.460Z",
      "__v": 0
    },
    {
      "_id": "69e3d9e27ceeabd32451d320",
      "name": "Look for Ramy",
      "garments": [
        "69dd8875035f6b5e0442ee23",
        "69e2bfb8541a1209ba5f88da"
      ],
      "previewImage": "https://res.cloudinary.com/dazn6zthy/image/upload/v1776126070/digital-wardrobe/image-1776126068455-5685221356410b7d.png.png",
      "previewImageMetadata": null,
      "isLookbook": false,
      "styledFor": "69dc95635bcfc7742725390a",
      "styleNote": "",
      "isSharedWithStyledUser": true,
      "owner": "69de030e1b0c613b1907833e",
      "createdAt": "2026-04-18T19:22:10.039Z",
      "updatedAt": "2026-04-18T19:22:10.039Z",
      "__v": 0
    },
    {
      "_id": "69e3dbbb7ceeabd32451d353",
      "name": "Ramy Look",
      "garments": [
        "69dca81f805be30ff653eba2",
        "69dca939805be30ff653ebde",
        "69dcaa60805be30ff653ebff",
        "69dcab7d805be30ff653ec2b"
      ],
      "previewImage": "https://res.cloudinary.com/dazn6zthy/image/upload/v1776076000/digital-wardrobe/image-1776075997597-7ee6a2b27f9d0339.png.png",
      "previewImageMetadata": null,
      "isLookbook": false,
      "styledFor": "69dc95635bcfc7742725390a",
      "styleNote": "Styled via Create Outfit canvas",
      "isSharedWithStyledUser": true,
      "owner": "69de030e1b0c613b1907833e",
      "createdAt": "2026-04-18T19:30:03.040Z",
      "updatedAt": "2026-04-18T19:30:03.040Z",
      "__v": 0
    }
  ],
  "users": [
    {
      "_id": "69dc95635bcfc7742725390a",
      "name": "Ramy",
      "email": "ramy.sameh2@gmail.com",
      "password": "$2b$10$o1Eb6uK4FsSt4/IN3wVVUetxq7co1Edu4gMsHpj0d02ABSfbso5lm",
      "profilePicture": "https://res.cloudinary.com/dazn6zthy/image/upload/v1776121481/digital-wardrobe/profileImage-1776121476366-9778aae522853a07.jpg.png",
      "profilePictureMetadata": {
        "imageUrl": "https://res.cloudinary.com/dazn6zthy/image/upload/v1776121481/digital-wardrobe/profileImage-1776121476366-9778aae522853a07.jpg.png",
        "provider": "cloudinary",
        "publicId": "digital-wardrobe/profileImage-1776121476366-9778aae522853a07.jpg",
        "secureUrl": "https://res.cloudinary.com/dazn6zthy/image/upload/v1776121481/digital-wardrobe/profileImage-1776121476366-9778aae522853a07.jpg.png",
        "assetId": "d38c50ae2a354f8e2afb46bb8c027915",
        "version": 1776121481,
        "resourceType": "image",
        "format": "png",
        "width": 685,
        "height": 686,
        "bytes": 785027,
        "mimeType": "image/png",
        "originalFilename": "profileImage-1776121477039.jpg",
        "uploadedAt": "2026-04-13T23:04:41.610Z"
      },
      "bannerImage": "https://res.cloudinary.com/dazn6zthy/image/upload/v1776076102/digital-wardrobe/bannerImage-1776076100726-3f51a7283d4de661.jpg.jpg",
      "bannerImageMetadata": {
        "imageUrl": "https://res.cloudinary.com/dazn6zthy/image/upload/v1776076102/digital-wardrobe/bannerImage-1776076100726-3f51a7283d4de661.jpg.jpg",
        "provider": "cloudinary",
        "publicId": "digital-wardrobe/bannerImage-1776076100726-3f51a7283d4de661.jpg",
        "secureUrl": "https://res.cloudinary.com/dazn6zthy/image/upload/v1776076102/digital-wardrobe/bannerImage-1776076100726-3f51a7283d4de661.jpg.jpg",
        "assetId": "56d4d72fc5eda14d788a71116f49d569",
        "version": 1776076102,
        "resourceType": "image",
        "format": "jpg",
        "width": 650,
        "height": 650,
        "bytes": 45244,
        "mimeType": "image/jpeg",
        "originalFilename": "bannerImage-1776076101499.jpg",
        "uploadedAt": "2026-04-13T10:28:22.029Z"
      },
      "bannerPreset": "pink",
      "age": null,
      "gender": "Male",
      "clothingSize": "M",
      "shoesSize": "44",
      "heightCm": 185,
      "weightKg": 75,
      "bodyType": null,
      "outfitFormula": "Casual & comfortable",
      "styleWords": [
        "Streetwear"
      ],
      "closetGoal": "Organize my outfits",
      "shoppingFrequency": "Monthly",
      "stylePreferences": [
        "Streetwear"
      ],
      "preferences": {
        "style": [],
        "favoriteColors": []
      },
      "createdAt": "2026-04-13T07:04:03.780Z",
      "updatedAt": "2026-04-18T18:58:13.157Z",
      "__v": 0,
      "followers": [
        "69de030e1b0c613b1907833e"
      ],
      "following": [
        "69de030e1b0c613b1907833e"
      ]
    },
    {
      "_id": "69de030e1b0c613b1907833e",
      "name": "lizzy liz",
      "email": "lougiineexlx@gmail.com",
      "password": "$2b$10$vKy.N6lDrVKWWzD8t8B1S.KtahW7PRN4TiGQKlAdGJfHAIBIZgSRK",
      "profilePicture": "https://res.cloudinary.com/dazn6zthy/image/upload/v1776157566/digital-wardrobe/profileImage-1776157564627-86189cf8e5c48308.jpg.jpg",
      "profilePictureMetadata": {
        "imageUrl": "https://res.cloudinary.com/dazn6zthy/image/upload/v1776157566/digital-wardrobe/profileImage-1776157564627-86189cf8e5c48308.jpg.jpg",
        "provider": "cloudinary",
        "publicId": "digital-wardrobe/profileImage-1776157564627-86189cf8e5c48308.jpg",
        "secureUrl": "https://res.cloudinary.com/dazn6zthy/image/upload/v1776157566/digital-wardrobe/profileImage-1776157564627-86189cf8e5c48308.jpg.jpg",
        "assetId": "9528db7f48ac8bb01d859471d0cf1161",
        "version": 1776157566,
        "resourceType": "image",
        "format": "jpg",
        "width": 1286,
        "height": 1287,
        "bytes": 363363,
        "mimeType": "image/jpeg",
        "originalFilename": "profileImage-1776157563642.jpg",
        "uploadedAt": "2026-04-14T09:06:08.056Z"
      },
      "bannerImage": "https://res.cloudinary.com/dazn6zthy/image/upload/v1776157658/digital-wardrobe/bannerImage-1776157657175-26a0da93b78ec0b7.jpg.jpg",
      "bannerImageMetadata": {
        "imageUrl": "https://res.cloudinary.com/dazn6zthy/image/upload/v1776157658/digital-wardrobe/bannerImage-1776157657175-26a0da93b78ec0b7.jpg.jpg",
        "provider": "cloudinary",
        "publicId": "digital-wardrobe/bannerImage-1776157657175-26a0da93b78ec0b7.jpg",
        "secureUrl": "https://res.cloudinary.com/dazn6zthy/image/upload/v1776157658/digital-wardrobe/bannerImage-1776157657175-26a0da93b78ec0b7.jpg.jpg",
        "assetId": "40d8d8a11fffac32410d92565a102b46",
        "version": 1776157658,
        "resourceType": "image",
        "format": "jpg",
        "width": 1287,
        "height": 1287,
        "bytes": 364469,
        "mimeType": "image/jpeg",
        "originalFilename": "bannerImage-1776157656235.jpg",
        "uploadedAt": "2026-04-14T09:07:40.688Z"
      },
      "bannerPreset": "pink",
      "age": null,
      "gender": "Female",
      "clothingSize": "XS",
      "shoesSize": "36",
      "heightCm": 150,
      "weightKg": 45,
      "bodyType": null,
      "outfitFormula": "Trendy & bold",
      "styleWords": [
        "Elegant"
      ],
      "closetGoal": "Organize my outfits",
      "shoppingFrequency": "Weekly",
      "stylePreferences": [],
      "preferences": {
        "style": [],
        "favoriteColors": []
      },
      "createdAt": "2026-04-14T09:04:14.445Z",
      "updatedAt": "2026-04-18T18:58:13.155Z",
      "__v": 0,
      "followers": [
        "69dc95635bcfc7742725390a"
      ],
      "following": [
        "69dc95635bcfc7742725390a"
      ]
    },
    {
      "_id": "69de144a3953eda9e5daea08",
      "name": "Copilot140012687",
      "email": "copilot_test_2008615430@example.com",
      "password": "$2b$10$skI7/QjxqSoEjAdk743RQu/N/SeYOFXIR3FLqv.qFtU2ujai5wjMm",
      "profilePicture": null,
      "profilePictureMetadata": null,
      "bannerImage": null,
      "bannerImageMetadata": null,
      "bannerPreset": "pink",
      "age": null,
      "gender": null,
      "clothingSize": null,
      "shoesSize": null,
      "heightCm": null,
      "weightKg": null,
      "bodyType": null,
      "outfitFormula": null,
      "styleWords": [],
      "closetGoal": null,
      "shoppingFrequency": null,
      "stylePreferences": [],
      "followers": [],
      "following": [],
      "preferences": {
        "style": [],
        "favoriteColors": []
      },
      "createdAt": "2026-04-14T10:17:46.451Z",
      "updatedAt": "2026-04-14T10:17:46.451Z",
      "__v": 0
    }
  ],
  "communitycomments": [],
  "garments": [
    {
      "_id": "69dc9fe8805be30ff653ea4c",
      "name": "Outerwear 2026-04-13",
      "category": "Outerwear",
      "color": "Black",
      "imageUrl": "https://res.cloudinary.com/dazn6zthy/image/upload/v1776075683/digital-wardrobe/image-1776075681042-5c9a5edfc1fb1027.png.png",
      "imageMetadata": {
        "imageUrl": "https://res.cloudinary.com/dazn6zthy/image/upload/v1776075683/digital-wardrobe/image-1776075681042-5c9a5edfc1fb1027.png.png",
        "provider": "cloudinary",
        "publicId": "digital-wardrobe/image-1776075681042-5c9a5edfc1fb1027.png",
        "secureUrl": "https://res.cloudinary.com/dazn6zthy/image/upload/v1776075683/digital-wardrobe/image-1776075681042-5c9a5edfc1fb1027.png.png",
        "assetId": "74fca7ff519cb1d1d513c05527780334",
        "version": 1776075683,
        "resourceType": "image",
        "format": "png",
        "width": 643,
        "height": 360,
        "bytes": 130652,
        "mimeType": "image/png",
        "originalFilename": "item-1776075680946.png",
        "uploadedAt": "2026-04-13T10:21:22.785Z"
      },
      "isFavorite": false,
      "isHidden": false,
      "owner": "69dc95635bcfc7742725390a",
      "createdAt": "2026-04-13T07:48:56.942Z",
      "updatedAt": "2026-04-14T03:29:48.789Z",
      "__v": 0,
      "purchasePrice": 2200
    },
    {
      "_id": "69dca254805be30ff653eaad",
      "name": "Footwear 2026-04-13",
      "category": "Footwear",
      "color": "Green",
      "imageUrl": "https://res.cloudinary.com/dazn6zthy/image/upload/v1776075732/digital-wardrobe/image-1776075730701-773a2e449cee3afb.png.png",
      "imageMetadata": {
        "imageUrl": "https://res.cloudinary.com/dazn6zthy/image/upload/v1776075732/digital-wardrobe/image-1776075730701-773a2e449cee3afb.png.png",
        "provider": "cloudinary",
        "publicId": "digital-wardrobe/image-1776075730701-773a2e449cee3afb.png",
        "secureUrl": "https://res.cloudinary.com/dazn6zthy/image/upload/v1776075732/digital-wardrobe/image-1776075730701-773a2e449cee3afb.png.png",
        "assetId": "8099a1d0d3c5bb5dc8dacbf64f3dcdee",
        "version": 1776075732,
        "resourceType": "image",
        "format": "png",
        "width": 500,
        "height": 500,
        "bytes": 151970,
        "mimeType": "image/png",
        "originalFilename": "item-1776075731301.png",
        "uploadedAt": "2026-04-13T10:22:12.599Z"
      },
      "isFavorite": false,
      "isHidden": false,
      "owner": "69dc95635bcfc7742725390a",
      "createdAt": "2026-04-13T07:59:16.054Z",
      "updatedAt": "2026-04-14T03:29:28.790Z",
      "__v": 0,
      "purchasePrice": 2000
    },
    {
      "_id": "69dca327805be30ff653eac2",
      "name": "Outerwear 2026-04-13",
      "category": "Outerwear",
      "color": "Blue",
      "imageUrl": "https://res.cloudinary.com/dazn6zthy/image/upload/v1776075800/digital-wardrobe/image-1776075794948-4573b13a417b2c35.png.png",
      "imageMetadata": {
        "imageUrl": "https://res.cloudinary.com/dazn6zthy/image/upload/v1776075800/digital-wardrobe/image-1776075794948-4573b13a417b2c35.png.png",
        "provider": "cloudinary",
        "publicId": "digital-wardrobe/image-1776075794948-4573b13a417b2c35.png",
        "secureUrl": "https://res.cloudinary.com/dazn6zthy/image/upload/v1776075800/digital-wardrobe/image-1776075794948-4573b13a417b2c35.png.png",
        "assetId": "e115b3de97031a721177bf66a11b9ac3",
        "version": 1776075800,
        "resourceType": "image",
        "format": "png",
        "width": 503,
        "height": 496,
        "bytes": 323461,
        "mimeType": "image/png",
        "originalFilename": "item-1776075792376.png",
        "uploadedAt": "2026-04-13T10:23:19.762Z"
      },
      "isFavorite": false,
      "isHidden": false,
      "owner": "69dc95635bcfc7742725390a",
      "createdAt": "2026-04-13T08:02:47.135Z",
      "updatedAt": "2026-04-14T03:29:11.754Z",
      "__v": 0,
      "purchasePrice": 1100
    },
    {
      "_id": "69dca76f805be30ff653eb4a",
      "name": "Outerwear 2026-04-13",
      "category": "Outerwear",
      "color": "Brown",
      "imageUrl": "https://res.cloudinary.com/dazn6zthy/image/upload/v1776075857/digital-wardrobe/image-1776075855073-b60d53f6064683e9.png.png",
      "imageMetadata": {
        "imageUrl": "https://res.cloudinary.com/dazn6zthy/image/upload/v1776075857/digital-wardrobe/image-1776075855073-b60d53f6064683e9.png.png",
        "provider": "cloudinary",
        "publicId": "digital-wardrobe/image-1776075855073-b60d53f6064683e9.png",
        "secureUrl": "https://res.cloudinary.com/dazn6zthy/image/upload/v1776075857/digital-wardrobe/image-1776075855073-b60d53f6064683e9.png.png",
        "assetId": "72424ccf234640c9452a2265a3a4e677",
        "version": 1776075857,
        "resourceType": "image",
        "format": "png",
        "width": 531,
        "height": 470,
        "bytes": 306411,
        "mimeType": "image/png",
        "originalFilename": "item-1776075853706.png",
        "uploadedAt": "2026-04-13T10:24:17.265Z"
      },
      "isFavorite": false,
      "isHidden": false,
      "owner": "69dc95635bcfc7742725390a",
      "createdAt": "2026-04-13T08:21:03.291Z",
      "updatedAt": "2026-04-14T03:28:56.647Z",
      "__v": 0,
      "purchasePrice": 1300
    },
    {
      "_id": "69dca81f805be30ff653eba2",
      "name": "Footwear 2026-04-13",
      "category": "Footwear",
      "color": "Brown",
      "imageUrl": "https://res.cloudinary.com/dazn6zthy/image/upload/v1776076000/digital-wardrobe/image-1776075997597-7ee6a2b27f9d0339.png.png",
      "imageMetadata": {
        "imageUrl": "https://res.cloudinary.com/dazn6zthy/image/upload/v1776076000/digital-wardrobe/image-1776075997597-7ee6a2b27f9d0339.png.png",
        "provider": "cloudinary",
        "publicId": "digital-wardrobe/image-1776075997597-7ee6a2b27f9d0339.png",
        "secureUrl": "https://res.cloudinary.com/dazn6zthy/image/upload/v1776076000/digital-wardrobe/image-1776075997597-7ee6a2b27f9d0339.png.png",
        "assetId": "3d2c375db64dec2b7ea7aa46aa7b7841",
        "version": 1776076000,
        "resourceType": "image",
        "format": "png",
        "width": 500,
        "height": 500,
        "bytes": 233195,
        "mimeType": "image/png",
        "originalFilename": "item-1776075998373.png",
        "uploadedAt": "2026-04-13T10:26:39.779Z"
      },
      "isFavorite": false,
      "isHidden": false,
      "owner": "69dc95635bcfc7742725390a",
      "createdAt": "2026-04-13T08:23:59.735Z",
      "updatedAt": "2026-04-14T03:28:41.492Z",
      "__v": 0,
      "purchasePrice": 3000
    },
    {
      "_id": "69dca87f805be30ff653ebd4",
      "name": "Footwear 2026-04-13",
      "category": "Footwear",
      "color": "Beige",
      "imageUrl": "https://res.cloudinary.com/dazn6zthy/image/upload/v1776075556/digital-wardrobe/image-1776075553428-7887ea20213d6179.png.png",
      "imageMetadata": {
        "imageUrl": "https://res.cloudinary.com/dazn6zthy/image/upload/v1776075556/digital-wardrobe/image-1776075553428-7887ea20213d6179.png.png",
        "provider": "cloudinary",
        "publicId": "digital-wardrobe/image-1776075553428-7887ea20213d6179.png",
        "secureUrl": "https://res.cloudinary.com/dazn6zthy/image/upload/v1776075556/digital-wardrobe/image-1776075553428-7887ea20213d6179.png.png",
        "assetId": "c25230a78fffe774cb53e80ae6141147",
        "version": 1776075556,
        "resourceType": "image",
        "format": "png",
        "width": 666,
        "height": 375,
        "bytes": 239012,
        "mimeType": "image/png",
        "originalFilename": "item-1776075549191.png",
        "uploadedAt": "2026-04-13T10:19:16.344Z"
      },
      "isFavorite": false,
      "isHidden": false,
      "owner": "69dc95635bcfc7742725390a",
      "createdAt": "2026-04-13T08:25:35.192Z",
      "updatedAt": "2026-04-14T03:28:24.964Z",
      "__v": 0,
      "purchasePrice": 1750
    },
    {
      "_id": "69dca915805be30ff653ebd9",
      "name": "Tops 2026-04-13",
      "category": "Tops",
      "color": "Blue",
      "imageUrl": "https://res.cloudinary.com/dazn6zthy/image/upload/v1776075469/digital-wardrobe/image-1776075467608-ab0aeacbe748507c.png.png",
      "imageMetadata": {
        "imageUrl": "https://res.cloudinary.com/dazn6zthy/image/upload/v1776075469/digital-wardrobe/image-1776075467608-ab0aeacbe748507c.png.png",
        "provider": "cloudinary",
        "publicId": "digital-wardrobe/image-1776075467608-ab0aeacbe748507c.png",
        "secureUrl": "https://res.cloudinary.com/dazn6zthy/image/upload/v1776075469/digital-wardrobe/image-1776075467608-ab0aeacbe748507c.png.png",
        "assetId": "d5c25e6220a958b4811ba8467772f318",
        "version": 1776075469,
        "resourceType": "image",
        "format": "png",
        "width": 408,
        "height": 612,
        "bytes": 102722,
        "mimeType": "image/png",
        "originalFilename": "item-1776075468216.png",
        "uploadedAt": "2026-04-13T10:17:49.030Z"
      },
      "isFavorite": false,
      "isHidden": false,
      "owner": "69dc95635bcfc7742725390a",
      "createdAt": "2026-04-13T08:28:05.677Z",
      "updatedAt": "2026-04-14T03:28:04.565Z",
      "__v": 0,
      "purchasePrice": 800
    },
    {
      "_id": "69dca939805be30ff653ebde",
      "name": "Tops 2026-04-13",
      "category": "Tops",
      "color": "Black",
      "imageUrl": "https://res.cloudinary.com/dazn6zthy/image/upload/v1776075383/digital-wardrobe/image-1776075381345-9d0ac8eba89540bc.png.png",
      "imageMetadata": {
        "imageUrl": "https://res.cloudinary.com/dazn6zthy/image/upload/v1776075383/digital-wardrobe/image-1776075381345-9d0ac8eba89540bc.png.png",
        "provider": "cloudinary",
        "publicId": "digital-wardrobe/image-1776075381345-9d0ac8eba89540bc.png",
        "secureUrl": "https://res.cloudinary.com/dazn6zthy/image/upload/v1776075383/digital-wardrobe/image-1776075381345-9d0ac8eba89540bc.png.png",
        "assetId": "3d37417869f13f117a4807c5637eee31",
        "version": 1776075383,
        "resourceType": "image",
        "format": "png",
        "width": 390,
        "height": 500,
        "bytes": 98708,
        "mimeType": "image/png",
        "originalFilename": "item-1776075381024.png",
        "uploadedAt": "2026-04-13T10:16:23.228Z"
      },
      "isFavorite": false,
      "isHidden": false,
      "owner": "69dc95635bcfc7742725390a",
      "createdAt": "2026-04-13T08:28:41.078Z",
      "updatedAt": "2026-04-14T03:27:49.405Z",
      "__v": 0,
      "purchasePrice": 900
    },
    {
      "_id": "69dca9c1805be30ff653ebe3",
      "name": "Tops 2026-04-13",
      "category": "Tops",
      "color": "Blue",
      "imageUrl": "https://res.cloudinary.com/dazn6zthy/image/upload/v1776075338/digital-wardrobe/image-1776075336402-b1a45e2ce3a7f0b8.png.png",
      "imageMetadata": {
        "imageUrl": "https://res.cloudinary.com/dazn6zthy/image/upload/v1776075338/digital-wardrobe/image-1776075336402-b1a45e2ce3a7f0b8.png.png",
        "provider": "cloudinary",
        "publicId": "digital-wardrobe/image-1776075336402-b1a45e2ce3a7f0b8.png",
        "secureUrl": "https://res.cloudinary.com/dazn6zthy/image/upload/v1776075338/digital-wardrobe/image-1776075336402-b1a45e2ce3a7f0b8.png.png",
        "assetId": "c6c4e0faf21bf01dbf7128bab77993ca",
        "version": 1776075338,
        "resourceType": "image",
        "format": "png",
        "width": 408,
        "height": 612,
        "bytes": 96830,
        "mimeType": "image/png",
        "originalFilename": "item-1776075336750.png",
        "uploadedAt": "2026-04-13T10:15:38.573Z"
      },
      "isFavorite": false,
      "isHidden": false,
      "owner": "69dc95635bcfc7742725390a",
      "createdAt": "2026-04-13T08:30:57.297Z",
      "updatedAt": "2026-04-14T03:27:33.630Z",
      "__v": 0,
      "purchasePrice": 1200
    },
    {
      "_id": "69dca9fd805be30ff653ebfa",
      "name": "Bottoms 2026-04-13",
      "category": "Bottoms",
      "color": "Brown",
      "imageUrl": "https://res.cloudinary.com/dazn6zthy/image/upload/v1776075296/digital-wardrobe/image-1776075293062-fb79d19f9589a84f.png.png",
      "imageMetadata": {
        "imageUrl": "https://res.cloudinary.com/dazn6zthy/image/upload/v1776075296/digital-wardrobe/image-1776075293062-fb79d19f9589a84f.png.png",
        "provider": "cloudinary",
        "publicId": "digital-wardrobe/image-1776075293062-fb79d19f9589a84f.png",
        "secureUrl": "https://res.cloudinary.com/dazn6zthy/image/upload/v1776075296/digital-wardrobe/image-1776075293062-fb79d19f9589a84f.png.png",
        "assetId": "7108e87c226ebc5f30ac4cf6a8e5eada",
        "version": 1776075296,
        "resourceType": "image",
        "format": "png",
        "width": 408,
        "height": 612,
        "bytes": 176460,
        "mimeType": "image/png",
        "originalFilename": "item-1776075293462.png",
        "uploadedAt": "2026-04-13T10:14:56.282Z"
      },
      "isFavorite": false,
      "isHidden": false,
      "owner": "69dc95635bcfc7742725390a",
      "createdAt": "2026-04-13T08:31:57.159Z",
      "updatedAt": "2026-04-14T03:27:19.144Z",
      "__v": 0,
      "purchasePrice": 1000
    },
    {
      "_id": "69dcaa60805be30ff653ebff",
      "name": "Bottoms 2026-04-13",
      "category": "Bottoms",
      "color": "Blue",
      "imageUrl": "https://res.cloudinary.com/dazn6zthy/image/upload/v1776075194/digital-wardrobe/image-1776075190471-4337a41aaa370183.png.png",
      "imageMetadata": {
        "imageUrl": "https://res.cloudinary.com/dazn6zthy/image/upload/v1776075194/digital-wardrobe/image-1776075190471-4337a41aaa370183.png.png",
        "provider": "cloudinary",
        "publicId": "digital-wardrobe/image-1776075190471-4337a41aaa370183.png",
        "secureUrl": "https://res.cloudinary.com/dazn6zthy/image/upload/v1776075194/digital-wardrobe/image-1776075190471-4337a41aaa370183.png.png",
        "assetId": "bf45bdbeeb81c555fe69c07cade7b083",
        "version": 1776075194,
        "resourceType": "image",
        "format": "png",
        "width": 426,
        "height": 586,
        "bytes": 291564,
        "mimeType": "image/png",
        "originalFilename": "item-1776075188484.png",
        "uploadedAt": "2026-04-13T10:13:14.627Z"
      },
      "isFavorite": false,
      "isHidden": false,
      "owner": "69dc95635bcfc7742725390a",
      "createdAt": "2026-04-13T08:33:36.313Z",
      "updatedAt": "2026-04-14T03:26:59.257Z",
      "__v": 0,
      "purchasePrice": 1700
    },
    {
      "_id": "69dcaa75805be30ff653ec04",
      "name": "Bottoms 2026-04-13",
      "category": "Bottoms",
      "color": "Black",
      "imageUrl": "https://res.cloudinary.com/dazn6zthy/image/upload/v1776075150/digital-wardrobe/image-1776075148865-d6cf0c363a791947.png.png",
      "imageMetadata": {
        "imageUrl": "https://res.cloudinary.com/dazn6zthy/image/upload/v1776075150/digital-wardrobe/image-1776075148865-d6cf0c363a791947.png.png",
        "provider": "cloudinary",
        "publicId": "digital-wardrobe/image-1776075148865-d6cf0c363a791947.png",
        "secureUrl": "https://res.cloudinary.com/dazn6zthy/image/upload/v1776075150/digital-wardrobe/image-1776075148865-d6cf0c363a791947.png.png",
        "assetId": "7662928d27aebd69f9fcc4773c653bb0",
        "version": 1776075150,
        "resourceType": "image",
        "format": "png",
        "width": 408,
        "height": 612,
        "bytes": 115876,
        "mimeType": "image/png",
        "originalFilename": "item-1776075149441.png",
        "uploadedAt": "2026-04-13T10:12:30.596Z"
      },
      "isFavorite": false,
      "isHidden": false,
      "owner": "69dc95635bcfc7742725390a",
      "createdAt": "2026-04-13T08:33:57.347Z",
      "updatedAt": "2026-04-14T03:26:45.376Z",
      "__v": 0,
      "purchasePrice": 1600
    },
    {
      "_id": "69dcaaa8805be30ff653ec21",
      "name": "Accessories 2026-04-13",
      "category": "Accessories",
      "color": "Brown",
      "imageUrl": "https://res.cloudinary.com/dazn6zthy/image/upload/v1776075077/digital-wardrobe/image-1776075075380-efd62a74febf2bb9.png.png",
      "imageMetadata": {
        "imageUrl": "https://res.cloudinary.com/dazn6zthy/image/upload/v1776075077/digital-wardrobe/image-1776075075380-efd62a74febf2bb9.png.png",
        "provider": "cloudinary",
        "publicId": "digital-wardrobe/image-1776075075380-efd62a74febf2bb9.png",
        "secureUrl": "https://res.cloudinary.com/dazn6zthy/image/upload/v1776075077/digital-wardrobe/image-1776075075380-efd62a74febf2bb9.png.png",
        "assetId": "4d6469c20cb7b965ed4228692a3ba34f",
        "version": 1776075077,
        "resourceType": "image",
        "format": "png",
        "width": 500,
        "height": 500,
        "bytes": 128030,
        "mimeType": "image/png",
        "originalFilename": "item-1776075076000.png",
        "uploadedAt": "2026-04-13T10:11:16.958Z"
      },
      "isFavorite": false,
      "isHidden": false,
      "owner": "69dc95635bcfc7742725390a",
      "createdAt": "2026-04-13T08:34:48.551Z",
      "updatedAt": "2026-04-14T03:26:30.751Z",
      "__v": 0,
      "purchasePrice": 150
    },
    {
      "_id": "69dcaadb805be30ff653ec26",
      "name": "Accessories 2026-04-13",
      "category": "Accessories",
      "color": "Red",
      "imageUrl": "https://res.cloudinary.com/dazn6zthy/image/upload/v1776075028/digital-wardrobe/image-1776075026231-9728ed7618a57d0b.png.png",
      "imageMetadata": {
        "imageUrl": "https://res.cloudinary.com/dazn6zthy/image/upload/v1776075028/digital-wardrobe/image-1776075026231-9728ed7618a57d0b.png.png",
        "provider": "cloudinary",
        "publicId": "digital-wardrobe/image-1776075026231-9728ed7618a57d0b.png",
        "secureUrl": "https://res.cloudinary.com/dazn6zthy/image/upload/v1776075028/digital-wardrobe/image-1776075026231-9728ed7618a57d0b.png.png",
        "assetId": "529d3edd063dcb2f5e42c9b9cbe769ef",
        "version": 1776075028,
        "resourceType": "image",
        "format": "png",
        "width": 500,
        "height": 500,
        "bytes": 243074,
        "mimeType": "image/png",
        "originalFilename": "item-1776075026852.png",
        "uploadedAt": "2026-04-13T10:10:28.287Z"
      },
      "isFavorite": false,
      "isHidden": false,
      "owner": "69dc95635bcfc7742725390a",
      "createdAt": "2026-04-13T08:35:39.716Z",
      "updatedAt": "2026-04-14T03:26:16.078Z",
      "__v": 0,
      "purchasePrice": 200
    },
    {
      "_id": "69dcab7d805be30ff653ec2b",
      "name": "Outerwear 2026-04-13",
      "category": "Outerwear",
      "color": "Red",
      "imageUrl": "https://res.cloudinary.com/dazn6zthy/image/upload/v1776074994/digital-wardrobe/image-1776074991839-cf22745e2ddf49f1.png.png",
      "imageMetadata": {
        "imageUrl": "https://res.cloudinary.com/dazn6zthy/image/upload/v1776074994/digital-wardrobe/image-1776074991839-cf22745e2ddf49f1.png.png",
        "provider": "cloudinary",
        "publicId": "digital-wardrobe/image-1776074991839-cf22745e2ddf49f1.png",
        "secureUrl": "https://res.cloudinary.com/dazn6zthy/image/upload/v1776074994/digital-wardrobe/image-1776074991839-cf22745e2ddf49f1.png.png",
        "assetId": "f4dd31f7e2ac3822dd09f8652d2e823b",
        "version": 1776074994,
        "resourceType": "image",
        "format": "png",
        "width": 434,
        "height": 575,
        "bytes": 159044,
        "mimeType": "image/png",
        "originalFilename": "item-1776074992368.png",
        "uploadedAt": "2026-04-13T10:09:54.037Z"
      },
      "isFavorite": false,
      "isHidden": false,
      "owner": "69dc95635bcfc7742725390a",
      "createdAt": "2026-04-13T08:38:21.427Z",
      "updatedAt": "2026-04-14T03:26:03.404Z",
      "__v": 0,
      "purchasePrice": 1100
    },
    {
      "_id": "69dcab8e805be30ff653ec30",
      "name": "Outerwear 2026-04-13",
      "category": "Outerwear",
      "color": "Green",
      "imageUrl": "https://res.cloudinary.com/dazn6zthy/image/upload/v1776074931/digital-wardrobe/image-1776074928847-9ad3f49bbca3f185.png.png",
      "imageMetadata": {
        "imageUrl": "https://res.cloudinary.com/dazn6zthy/image/upload/v1776074931/digital-wardrobe/image-1776074928847-9ad3f49bbca3f185.png.png",
        "provider": "cloudinary",
        "publicId": "digital-wardrobe/image-1776074928847-9ad3f49bbca3f185.png",
        "secureUrl": "https://res.cloudinary.com/dazn6zthy/image/upload/v1776074931/digital-wardrobe/image-1776074928847-9ad3f49bbca3f185.png.png",
        "assetId": "bca4503474fb75d16c4d9976fe4df2a4",
        "version": 1776074931,
        "resourceType": "image",
        "format": "png",
        "width": 433,
        "height": 577,
        "bytes": 185264,
        "mimeType": "image/png",
        "originalFilename": "item-1776074929424.png",
        "uploadedAt": "2026-04-13T10:08:51.931Z"
      },
      "isFavorite": false,
      "isHidden": false,
      "owner": "69dc95635bcfc7742725390a",
      "createdAt": "2026-04-13T08:38:38.595Z",
      "updatedAt": "2026-04-14T03:25:33.202Z",
      "__v": 0,
      "purchasePrice": 900
    },
    {
      "_id": "69dcab9f805be30ff653ec35",
      "name": "Outerwear 2026-04-13",
      "category": "Outerwear",
      "color": "Beige",
      "imageUrl": "https://res.cloudinary.com/dazn6zthy/image/upload/v1776074888/digital-wardrobe/image-1776074885844-92d6ee1a507433a4.png.png",
      "imageMetadata": {
        "imageUrl": "https://res.cloudinary.com/dazn6zthy/image/upload/v1776074888/digital-wardrobe/image-1776074885844-92d6ee1a507433a4.png.png",
        "provider": "cloudinary",
        "publicId": "digital-wardrobe/image-1776074885844-92d6ee1a507433a4.png",
        "secureUrl": "https://res.cloudinary.com/dazn6zthy/image/upload/v1776074888/digital-wardrobe/image-1776074885844-92d6ee1a507433a4.png.png",
        "assetId": "243f59d4b5e1a947cdd016b748bc600c",
        "version": 1776074888,
        "resourceType": "image",
        "format": "png",
        "width": 500,
        "height": 500,
        "bytes": 186290,
        "mimeType": "image/png",
        "originalFilename": "item-1776074886420.png",
        "uploadedAt": "2026-04-13T10:08:08.565Z"
      },
      "isFavorite": false,
      "isHidden": false,
      "owner": "69dc95635bcfc7742725390a",
      "createdAt": "2026-04-13T08:38:55.772Z",
      "updatedAt": "2026-04-14T03:24:59.289Z",
      "__v": 0,
      "purchasePrice": 1000
    },
    {
      "_id": "69dcabe5805be30ff653ec3a",
      "name": "Tops 2026-04-13",
      "category": "Tops",
      "color": "White",
      "imageUrl": "https://res.cloudinary.com/dazn6zthy/image/upload/v1776074818/digital-wardrobe/image-1776074816442-db5ba95ee0abaffa.png.png",
      "imageMetadata": {
        "imageUrl": "https://res.cloudinary.com/dazn6zthy/image/upload/v1776074818/digital-wardrobe/image-1776074816442-db5ba95ee0abaffa.png.png",
        "provider": "cloudinary",
        "publicId": "digital-wardrobe/image-1776074816442-db5ba95ee0abaffa.png",
        "secureUrl": "https://res.cloudinary.com/dazn6zthy/image/upload/v1776074818/digital-wardrobe/image-1776074816442-db5ba95ee0abaffa.png.png",
        "assetId": "0d068324cd013a22ad3705e38b4fff4d",
        "version": 1776074818,
        "resourceType": "image",
        "format": "png",
        "width": 408,
        "height": 612,
        "bytes": 106202,
        "mimeType": "image/png",
        "originalFilename": "item-1776074817020.png",
        "uploadedAt": "2026-04-13T10:06:58.273Z"
      },
      "isFavorite": false,
      "isHidden": false,
      "owner": "69dc95635bcfc7742725390a",
      "createdAt": "2026-04-13T08:40:05.403Z",
      "updatedAt": "2026-04-14T03:24:38.689Z",
      "__v": 0,
      "purchasePrice": 800
    },
    {
      "_id": "69dcac0d805be30ff653ec3f",
      "name": "Tops 2026-04-13",
      "category": "Tops",
      "color": "Navy",
      "imageUrl": "https://res.cloudinary.com/dazn6zthy/image/upload/v1776074703/digital-wardrobe/image-1776074701820-2fc482f9b4ce18ed.png.png",
      "imageMetadata": {
        "imageUrl": "https://res.cloudinary.com/dazn6zthy/image/upload/v1776074703/digital-wardrobe/image-1776074701820-2fc482f9b4ce18ed.png.png",
        "provider": "cloudinary",
        "publicId": "digital-wardrobe/image-1776074701820-2fc482f9b4ce18ed.png",
        "secureUrl": "https://res.cloudinary.com/dazn6zthy/image/upload/v1776074703/digital-wardrobe/image-1776074701820-2fc482f9b4ce18ed.png.png",
        "assetId": "00e0225359c4b5a2a2a66cd42c210f3c",
        "version": 1776074703,
        "resourceType": "image",
        "format": "png",
        "width": 330,
        "height": 413,
        "bytes": 50931,
        "mimeType": "image/png",
        "originalFilename": "item-1776074702386.png",
        "uploadedAt": "2026-04-13T10:05:03.336Z"
      },
      "isFavorite": false,
      "isHidden": false,
      "owner": "69dc95635bcfc7742725390a",
      "createdAt": "2026-04-13T08:40:45.239Z",
      "updatedAt": "2026-04-14T03:24:24.795Z",
      "__v": 0,
      "purchasePrice": 500
    },
    {
      "_id": "69dd86fc035f6b5e0442edd2",
      "name": "Tops 2026-04-14",
      "category": "Tops",
      "color": "Yellow",
      "imageUrl": "https://res.cloudinary.com/dazn6zthy/image/upload/v1776125692/digital-wardrobe/image-1776125690634-4ea8935e504a2b90.png.png",
      "imageMetadata": {
        "imageUrl": "https://res.cloudinary.com/dazn6zthy/image/upload/v1776125692/digital-wardrobe/image-1776125690634-4ea8935e504a2b90.png.png",
        "provider": "cloudinary",
        "publicId": "digital-wardrobe/image-1776125690634-4ea8935e504a2b90.png",
        "secureUrl": "https://res.cloudinary.com/dazn6zthy/image/upload/v1776125692/digital-wardrobe/image-1776125690634-4ea8935e504a2b90.png.png",
        "assetId": "3c629e43cee0563379a93cb2deb22f9f",
        "version": 1776125692,
        "resourceType": "image",
        "format": "png",
        "width": 408,
        "height": 612,
        "bytes": 121468,
        "mimeType": "image/png",
        "originalFilename": "image-1776125691343.png",
        "uploadedAt": "2026-04-14T00:14:52.268Z"
      },
      "isFavorite": false,
      "isHidden": false,
      "owner": "69dc95635bcfc7742725390a",
      "createdAt": "2026-04-14T00:14:52.270Z",
      "updatedAt": "2026-04-14T03:24:11.221Z",
      "__v": 0,
      "purchasePrice": 300
    },
    {
      "_id": "69dd8875035f6b5e0442ee23",
      "name": "Outerwear 2026-04-14",
      "category": "Outerwear",
      "color": "Black",
      "imageUrl": "https://res.cloudinary.com/dazn6zthy/image/upload/v1776126070/digital-wardrobe/image-1776126068455-5685221356410b7d.png.png",
      "imageMetadata": {
        "imageUrl": "https://res.cloudinary.com/dazn6zthy/image/upload/v1776126070/digital-wardrobe/image-1776126068455-5685221356410b7d.png.png",
        "provider": "cloudinary",
        "publicId": "digital-wardrobe/image-1776126068455-5685221356410b7d.png",
        "secureUrl": "https://res.cloudinary.com/dazn6zthy/image/upload/v1776126070/digital-wardrobe/image-1776126068455-5685221356410b7d.png.png",
        "assetId": "c187adc3417205c26a5e5dfc772d5f22",
        "version": 1776126070,
        "resourceType": "image",
        "format": "png",
        "width": 386,
        "height": 388,
        "bytes": 68458,
        "mimeType": "image/png",
        "originalFilename": "image-1776126069136.png",
        "uploadedAt": "2026-04-14T00:21:09.907Z"
      },
      "isFavorite": false,
      "isHidden": false,
      "owner": "69dc95635bcfc7742725390a",
      "createdAt": "2026-04-14T00:21:09.909Z",
      "updatedAt": "2026-04-14T03:23:59.722Z",
      "__v": 0,
      "purchasePrice": 800
    },
    {
      "_id": "69e2bf58541a1209ba5f88a8",
      "name": "Bottoms 2026-04-17",
      "category": "Bottoms",
      "color": "Green",
      "imageUrl": "https://res.cloudinary.com/dazn6zthy/image/upload/v1776467803/digital-wardrobe/image-1776467798522-ce750eabf7ef2e2c.png.png",
      "imageMetadata": {
        "imageUrl": "https://res.cloudinary.com/dazn6zthy/image/upload/v1776467803/digital-wardrobe/image-1776467798522-ce750eabf7ef2e2c.png.png",
        "provider": "cloudinary",
        "publicId": "digital-wardrobe/image-1776467798522-ce750eabf7ef2e2c.png",
        "secureUrl": "https://res.cloudinary.com/dazn6zthy/image/upload/v1776467803/digital-wardrobe/image-1776467798522-ce750eabf7ef2e2c.png.png",
        "assetId": "c07afb7723904b09203bd555f675833c",
        "version": 1776467803,
        "resourceType": "image",
        "format": "png",
        "width": 500,
        "height": 500,
        "bytes": 214030,
        "mimeType": "image/png",
        "originalFilename": "image-1776467801918.png",
        "uploadedAt": "2026-04-17T23:16:40.853Z"
      },
      "isFavorite": false,
      "isHidden": false,
      "owner": "69dc95635bcfc7742725390a",
      "createdAt": "2026-04-17T23:16:40.861Z",
      "updatedAt": "2026-04-17T23:16:40.861Z",
      "__v": 0
    },
    {
      "_id": "69e2bfb8541a1209ba5f88da",
      "name": "Footwear 2026-04-17",
      "category": "Footwear",
      "color": "Black",
      "imageUrl": "https://res.cloudinary.com/dazn6zthy/image/upload/v1776467899/digital-wardrobe/image-1776467894387-d140d9449fba2d30.png.png",
      "imageMetadata": {
        "imageUrl": "https://res.cloudinary.com/dazn6zthy/image/upload/v1776467899/digital-wardrobe/image-1776467894387-d140d9449fba2d30.png.png",
        "provider": "cloudinary",
        "publicId": "digital-wardrobe/image-1776467894387-d140d9449fba2d30.png",
        "secureUrl": "https://res.cloudinary.com/dazn6zthy/image/upload/v1776467899/digital-wardrobe/image-1776467894387-d140d9449fba2d30.png.png",
        "assetId": "a35e51ae815d191322b1effd5788762b",
        "version": 1776467899,
        "resourceType": "image",
        "format": "png",
        "width": 500,
        "height": 500,
        "bytes": 232722,
        "mimeType": "image/png",
        "originalFilename": "image-1776467897779.png",
        "uploadedAt": "2026-04-17T23:18:16.610Z"
      },
      "isFavorite": false,
      "isHidden": false,
      "owner": "69dc95635bcfc7742725390a",
      "createdAt": "2026-04-17T23:18:16.611Z",
      "updatedAt": "2026-04-17T23:18:16.611Z",
      "__v": 0
    },
    {
      "_id": "69e3d43d7ceeabd32451d196",
      "name": "Footwear 2026-04-18",
      "category": "Footwear",
      "color": "Black",
      "imageUrl": "https://res.cloudinary.com/dazn6zthy/image/upload/v1776538685/digital-wardrobe/image-1776538684341-272cecc5830046d1.png.png",
      "imageMetadata": {
        "imageUrl": "https://res.cloudinary.com/dazn6zthy/image/upload/v1776538685/digital-wardrobe/image-1776538684341-272cecc5830046d1.png.png",
        "provider": "cloudinary",
        "publicId": "digital-wardrobe/image-1776538684341-272cecc5830046d1.png",
        "secureUrl": "https://res.cloudinary.com/dazn6zthy/image/upload/v1776538685/digital-wardrobe/image-1776538684341-272cecc5830046d1.png.png",
        "assetId": "cde1e0fc3184f6de57199aabca36299c",
        "version": 1776538685,
        "resourceType": "image",
        "format": "png",
        "width": 463,
        "height": 280,
        "bytes": 71387,
        "mimeType": "image/png",
        "originalFilename": "image-1776538684482.png",
        "uploadedAt": "2026-04-18T18:58:05.994Z"
      },
      "isFavorite": false,
      "isHidden": false,
      "owner": "69de030e1b0c613b1907833e",
      "createdAt": "2026-04-18T18:58:06.000Z",
      "updatedAt": "2026-04-18T18:58:06.000Z",
      "__v": 0
    }
  ],
  "communityposts": [
    {
      "_id": "69e3d8d47ceeabd32451d2e7",
      "author": "69de030e1b0c613b1907833e",
      "type": "post",
      "caption": "Styled an outfit for @Ramy: Look for Ramy",
      "imageUrl": "https://res.cloudinary.com/dazn6zthy/image/upload/v1776125692/digital-wardrobe/image-1776125690634-4ea8935e504a2b90.png.png",
      "tags": [
        "styled-for:69dc95635bcfc7742725390a"
      ],
      "likes": [],
      "commentsCount": 0,
      "poll": {
        "question": null,
        "endsAt": null,
        "options": []
      },
      "createdAt": "2026-04-18T19:17:40.530Z",
      "updatedAt": "2026-04-18T19:17:40.530Z",
      "__v": 0
    },
    {
      "_id": "69e3d9e27ceeabd32451d322",
      "author": "69de030e1b0c613b1907833e",
      "type": "post",
      "caption": "Styled an outfit for @Ramy: Look for Ramy",
      "imageUrl": "https://res.cloudinary.com/dazn6zthy/image/upload/v1776126070/digital-wardrobe/image-1776126068455-5685221356410b7d.png.png",
      "tags": [
        "styled-for:69dc95635bcfc7742725390a"
      ],
      "likes": [],
      "commentsCount": 0,
      "poll": {
        "question": null,
        "endsAt": null,
        "options": []
      },
      "createdAt": "2026-04-18T19:22:10.105Z",
      "updatedAt": "2026-04-18T19:22:10.105Z",
      "__v": 0
    },
    {
      "_id": "69e3dbbb7ceeabd32451d355",
      "author": "69de030e1b0c613b1907833e",
      "type": "post",
      "caption": "Styled an outfit for @Ramy: Ramy Look - Styled via Create Outfit canvas",
      "imageUrl": "https://res.cloudinary.com/dazn6zthy/image/upload/v1776076000/digital-wardrobe/image-1776075997597-7ee6a2b27f9d0339.png.png",
      "tags": [
        "styled-for:69dc95635bcfc7742725390a"
      ],
      "likes": [],
      "commentsCount": 0,
      "poll": {
        "question": null,
        "endsAt": null,
        "options": []
      },
      "createdAt": "2026-04-18T19:30:03.102Z",
      "updatedAt": "2026-04-18T19:30:03.102Z",
      "__v": 0
    }
  ],
  "usages": [
    {
      "_id": "69dcac5c805be30ff653ec8f",
      "user": "69dc95635bcfc7742725390a",
      "garment": "69dca76f805be30ff653eb4a",
      "outfit": "69dcac5c805be30ff653ec8d",
      "wornDate": "2026-04-13T08:42:04.498Z",
      "__v": 0,
      "createdAt": "2026-04-13T08:42:04.500Z",
      "updatedAt": "2026-04-13T08:42:04.500Z"
    },
    {
      "_id": "69dcac5c805be30ff653ec90",
      "user": "69dc95635bcfc7742725390a",
      "garment": "69dcabe5805be30ff653ec3a",
      "outfit": "69dcac5c805be30ff653ec8d",
      "wornDate": "2026-04-13T08:42:04.498Z",
      "__v": 0,
      "createdAt": "2026-04-13T08:42:04.500Z",
      "updatedAt": "2026-04-13T08:42:04.500Z"
    },
    {
      "_id": "69dcac5c805be30ff653ec91",
      "user": "69dc95635bcfc7742725390a",
      "garment": "69dca9fd805be30ff653ebfa",
      "outfit": "69dcac5c805be30ff653ec8d",
      "wornDate": "2026-04-13T08:42:04.498Z",
      "__v": 0,
      "createdAt": "2026-04-13T08:42:04.500Z",
      "updatedAt": "2026-04-13T08:42:04.500Z"
    },
    {
      "_id": "69dcac5c805be30ff653ec92",
      "user": "69dc95635bcfc7742725390a",
      "garment": "69dca81f805be30ff653eba2",
      "outfit": "69dcac5c805be30ff653ec8d",
      "wornDate": "2026-04-13T08:42:04.498Z",
      "__v": 0,
      "createdAt": "2026-04-13T08:42:04.500Z",
      "updatedAt": "2026-04-13T08:42:04.500Z"
    },
    {
      "_id": "69dcac6d805be30ff653ec97",
      "user": "69dc95635bcfc7742725390a",
      "garment": "69dc9fe8805be30ff653ea4c",
      "outfit": "69dcac6d805be30ff653ec95",
      "wornDate": "2026-04-13T08:42:21.987Z",
      "__v": 0,
      "createdAt": "2026-04-13T08:42:21.987Z",
      "updatedAt": "2026-04-13T08:42:21.987Z"
    },
    {
      "_id": "69dcac6d805be30ff653ec98",
      "user": "69dc95635bcfc7742725390a",
      "garment": "69dcac0d805be30ff653ec3f",
      "outfit": "69dcac6d805be30ff653ec95",
      "wornDate": "2026-04-13T08:42:21.987Z",
      "__v": 0,
      "createdAt": "2026-04-13T08:42:21.987Z",
      "updatedAt": "2026-04-13T08:42:21.987Z"
    },
    {
      "_id": "69dcac6d805be30ff653ec99",
      "user": "69dc95635bcfc7742725390a",
      "garment": "69dcaa75805be30ff653ec04",
      "outfit": "69dcac6d805be30ff653ec95",
      "wornDate": "2026-04-13T08:42:21.987Z",
      "__v": 0,
      "createdAt": "2026-04-13T08:42:21.987Z",
      "updatedAt": "2026-04-13T08:42:21.987Z"
    },
    {
      "_id": "69dcac6d805be30ff653ec9a",
      "user": "69dc95635bcfc7742725390a",
      "garment": "69dca87f805be30ff653ebd4",
      "outfit": "69dcac6d805be30ff653ec95",
      "wornDate": "2026-04-13T08:42:21.987Z",
      "__v": 0,
      "createdAt": "2026-04-13T08:42:21.987Z",
      "updatedAt": "2026-04-13T08:42:21.987Z"
    },
    {
      "_id": "69dcac79805be30ff653ec9f",
      "user": "69dc95635bcfc7742725390a",
      "garment": "69dcaa75805be30ff653ec04",
      "outfit": "69dcac79805be30ff653ec9d",
      "wornDate": "2026-04-13T08:42:33.480Z",
      "__v": 0,
      "createdAt": "2026-04-13T08:42:33.481Z",
      "updatedAt": "2026-04-13T08:42:33.481Z"
    },
    {
      "_id": "69dcac79805be30ff653eca0",
      "user": "69dc95635bcfc7742725390a",
      "garment": "69dca9c1805be30ff653ebe3",
      "outfit": "69dcac79805be30ff653ec9d",
      "wornDate": "2026-04-13T08:42:33.480Z",
      "__v": 0,
      "createdAt": "2026-04-13T08:42:33.481Z",
      "updatedAt": "2026-04-13T08:42:33.481Z"
    },
    {
      "_id": "69dcac79805be30ff653eca1",
      "user": "69dc95635bcfc7742725390a",
      "garment": "69dca76f805be30ff653eb4a",
      "outfit": "69dcac79805be30ff653ec9d",
      "wornDate": "2026-04-13T08:42:33.480Z",
      "__v": 0,
      "createdAt": "2026-04-13T08:42:33.481Z",
      "updatedAt": "2026-04-13T08:42:33.481Z"
    },
    {
      "_id": "69dcac79805be30ff653eca2",
      "user": "69dc95635bcfc7742725390a",
      "garment": "69dca87f805be30ff653ebd4",
      "outfit": "69dcac79805be30ff653ec9d",
      "wornDate": "2026-04-13T08:42:33.480Z",
      "__v": 0,
      "createdAt": "2026-04-13T08:42:33.481Z",
      "updatedAt": "2026-04-13T08:42:33.481Z"
    },
    {
      "_id": "69dcac89805be30ff653eca7",
      "user": "69dc95635bcfc7742725390a",
      "garment": "69dca254805be30ff653eaad",
      "outfit": "69dcac89805be30ff653eca5",
      "wornDate": "2026-04-13T08:42:49.277Z",
      "__v": 0,
      "createdAt": "2026-04-13T08:42:49.277Z",
      "updatedAt": "2026-04-13T08:42:49.277Z"
    },
    {
      "_id": "69dcac89805be30ff653eca8",
      "user": "69dc95635bcfc7742725390a",
      "garment": "69dcaa60805be30ff653ebff",
      "outfit": "69dcac89805be30ff653eca5",
      "wornDate": "2026-04-13T08:42:49.277Z",
      "__v": 0,
      "createdAt": "2026-04-13T08:42:49.277Z",
      "updatedAt": "2026-04-13T08:42:49.277Z"
    },
    {
      "_id": "69dcac89805be30ff653eca9",
      "user": "69dc95635bcfc7742725390a",
      "garment": "69dcabe5805be30ff653ec3a",
      "outfit": "69dcac89805be30ff653eca5",
      "wornDate": "2026-04-13T08:42:49.277Z",
      "__v": 0,
      "createdAt": "2026-04-13T08:42:49.277Z",
      "updatedAt": "2026-04-13T08:42:49.277Z"
    },
    {
      "_id": "69dcac89805be30ff653ecaa",
      "user": "69dc95635bcfc7742725390a",
      "garment": "69dcab8e805be30ff653ec30",
      "outfit": "69dcac89805be30ff653eca5",
      "wornDate": "2026-04-13T08:42:49.277Z",
      "__v": 0,
      "createdAt": "2026-04-13T08:42:49.277Z",
      "updatedAt": "2026-04-13T08:42:49.277Z"
    },
    {
      "_id": "69dcadbc805be30ff653ecf1",
      "user": "69dc95635bcfc7742725390a",
      "garment": "69dca254805be30ff653eaad",
      "outfit": "69dcadbc805be30ff653ecef",
      "wornDate": "2026-04-13T08:47:56.363Z",
      "__v": 0,
      "createdAt": "2026-04-13T08:47:56.364Z",
      "updatedAt": "2026-04-13T08:47:56.364Z"
    },
    {
      "_id": "69dcadbc805be30ff653ecf2",
      "user": "69dc95635bcfc7742725390a",
      "garment": "69dcaa60805be30ff653ebff",
      "outfit": "69dcadbc805be30ff653ecef",
      "wornDate": "2026-04-13T08:47:56.363Z",
      "__v": 0,
      "createdAt": "2026-04-13T08:47:56.364Z",
      "updatedAt": "2026-04-13T08:47:56.364Z"
    },
    {
      "_id": "69dcadbc805be30ff653ecf3",
      "user": "69dc95635bcfc7742725390a",
      "garment": "69dcabe5805be30ff653ec3a",
      "outfit": "69dcadbc805be30ff653ecef",
      "wornDate": "2026-04-13T08:47:56.363Z",
      "__v": 0,
      "createdAt": "2026-04-13T08:47:56.364Z",
      "updatedAt": "2026-04-13T08:47:56.364Z"
    }
  ]
}