[
  {
    "name": "Black Jacket",
    "type": "jacket",
    "color": "black",
    "season": "mild",
    "occasion": "casual",
    "gender": "male",
    "imageUrl": "https://res.cloudinary.com/dazn6zthy/image/upload/v1776075683/digital-wardrobe/image-1776075681042-5c9a5edfc1fb1027.png.png",
    "price": 2200,
    "wearCount": 0
  },
  {
    "name": "Green Shoes",
    "type": "shoes",
    "color": "green",
    "season": "mild",
    "occasion": "casual",
    "gender": "male",
    "imageUrl": "https://res.cloudinary.com/dazn6zthy/image/upload/v1776075732/digital-wardrobe/image-1776075730701-773a2e449cee3afb.png.png",
    "price": 2000,
    "wearCount": 0
  },
  {
    "name": "Blue Jacket",
    "type": "jacket",
    "color": "blue",
    "season": "mild",
    "occasion": "casual",
    "gender": "male",
    "imageUrl": "https://res.cloudinary.com/dazn6zthy/image/upload/v1776075800/digital-wardrobe/image-1776075794948-4573b13a417b2c35.png.png",
    "price": 1100,
    "wearCount": 0
  },
  {
    "name": "Brown Jacket",
    "type": "jacket",
    "color": "brown",
    "season": "mild",
    "occasion": "casual",
    "gender": "male",
    "imageUrl": "https://res.cloudinary.com/dazn6zthy/image/upload/v1776075857/digital-wardrobe/image-1776075855073-b60d53f6064683e9.png.png",
    "price": 1300,
    "wearCount": 0
  },
  {
    "name": "Brown Shoes",
    "type": "shoes",
    "color": "brown",
    "season": "mild",
    "occasion": "formal",
    "gender": "male",
    "imageUrl": "https://res.cloudinary.com/dazn6zthy/image/upload/v1776076000/digital-wardrobe/image-1776075997597-7ee6a2b27f9d0339.png.png",
    "price": 3000,
    "wearCount": 0
  },
  {
    "name": "Beige Shoes",
    "type": "shoes",
    "color": "beige",
    "season": "mild",
    "occasion": "casual",
    "gender": "male",
    "imageUrl": "https://res.cloudinary.com/dazn6zthy/image/upload/v1776075556/digital-wardrobe/image-1776075553428-7887ea20213d6179.png.png",
    "price": 1750,
    "wearCount": 0
  },
  {
    "name": "Blue Tshirt",
    "type": "tshirt",
    "color": "blue",
    "season": "mild",
    "occasion": "casual",
    "gender": "male",
    "imageUrl": "https://res.cloudinary.com/dazn6zthy/image/upload/v1776075469/digital-wardrobe/image-1776075467608-ab0aeacbe748507c.png.png",
    "price": 800,
    "wearCount": 0
  },
  {
    "name": "Black Tshirt",
    "type": "tshirt",
    "color": "black",
    "season": "mild",
    "occasion": "casual",
    "gender": "male",
    "imageUrl": "https://res.cloudinary.com/dazn6zthy/image/upload/v1776075383/digital-wardrobe/image-1776075381345-9d0ac8eba89540bc.png.png",
    "price": 900,
    "wearCount": 0
  },
  {
    "name": "Blue Tshirt",
    "type": "tshirt",
    "color": "blue",
    "season": "mild",
    "occasion": "casual",
    "gender": "male",
    "imageUrl": "https://res.cloudinary.com/dazn6zthy/image/upload/v1776075338/digital-wardrobe/image-1776075336402-b1a45e2ce3a7f0b8.png.png",
    "price": 1200,
    "wearCount": 0
  },
  {
    "name": "Brown Pants",
    "type": "pants",
    "color": "brown",
    "season": "mild",
    "occasion": "casual",
    "gender": "male",
    "imageUrl": "https://res.cloudinary.com/dazn6zthy/image/upload/v1776075296/digital-wardrobe/image-1776075293062-fb79d19f9589a84f.png.png",
    "price": 1000,
    "wearCount": 0
  },
  {
    "name": "Blue Pants",
    "type": "pants",
    "color": "blue",
    "season": "mild",
    "occasion": "casual",
    "gender": "male",
    "imageUrl": "https://res.cloudinary.com/dazn6zthy/image/upload/v1776075194/digital-wardrobe/image-1776075190471-4337a41aaa370183.png.png",
    "price": 1700,
    "wearCount": 0
  },
  {
    "name": "Black Pants",
    "type": "pants",
    "color": "black",
    "season": "mild",
    "occasion": "casual",
    "gender": "male",
    "imageUrl": "https://res.cloudinary.com/dazn6zthy/image/upload/v1776075150/digital-wardrobe/image-1776075148865-d6cf0c363a791947.png.png",
    "price": 1600,
    "wearCount": 0
  },
  {
    "name": "Red Jacket",
    "type": "jacket",
    "color": "red",
    "season": "mild",
    "occasion": "casual",
    "gender": "male",
    "imageUrl": "https://res.cloudinary.com/dazn6zthy/image/upload/v1776074994/digital-wardrobe/image-1776074991839-cf22745e2ddf49f1.png.png",
    "price": 1100,
    "wearCount": 0
  },
  {
    "name": "Green Jacket",
    "type": "jacket",
    "color": "green",
    "season": "mild",
    "occasion": "casual",
    "gender": "male",
    "imageUrl": "https://res.cloudinary.com/dazn6zthy/image/upload/v1776074931/digital-wardrobe/image-1776074928847-9ad3f49bbca3f185.png.png",
    "price": 900,
    "wearCount": 0
  },
  {
    "name": "Beige Jacket",
    "type": "jacket",
    "color": "beige",
    "season": "mild",
    "occasion": "casual",
    "gender": "male",
    "imageUrl": "https://res.cloudinary.com/dazn6zthy/image/upload/v1776074888/digital-wardrobe/image-1776074885844-92d6ee1a507433a4.png.png",
    "price": 1000,
    "wearCount": 0
  },
  {
    "name": "White Tshirt",
    "type": "tshirt",
    "color": "white",
    "season": "mild",
    "occasion": "casual",
    "gender": "male",
    "imageUrl": "https://res.cloudinary.com/dazn6zthy/image/upload/v1776074818/digital-wardrobe/image-1776074816442-db5ba95ee0abaffa.png.png",
    "price": 800,
    "wearCount": 0
  },
  {
    "name": "Navy Tshirt",
    "type": "tshirt",
    "color": "navy",
    "season": "mild",
    "occasion": "casual",
    "gender": "male",
    "imageUrl": "https://res.cloudinary.com/dazn6zthy/image/upload/v1776074703/digital-wardrobe/image-1776074701820-2fc482f9b4ce18ed.png.png",
    "price": 500,
    "wearCount": 0
  },
  {
    "name": "Yellow Tshirt",
    "type": "tshirt",
    "color": "yellow",
    "season": "mild",
    "occasion": "casual",
    "gender": "male",
    "imageUrl": "https://res.cloudinary.com/dazn6zthy/image/upload/v1776125692/digital-wardrobe/image-1776125690634-4ea8935e504a2b90.png.png",
    "price": 300,
    "wearCount": 0
  },
  {
    "name": "Black Jacket",
    "type": "jacket",
    "color": "black",
    "season": "mild",
    "occasion": "casual",
    "gender": "male",
    "imageUrl": "https://res.cloudinary.com/dazn6zthy/image/upload/v1776126070/digital-wardrobe/image-1776126068455-5685221356410b7d.png.png",
    "price": 800,
    "wearCount": 0
  },
  {
    "name": "Green Pants",
    "type": "pants",
    "color": "green",
    "season": "mild",
    "occasion": "casual",
    "gender": "male",
    "imageUrl": "https://res.cloudinary.com/dazn6zthy/image/upload/v1776467803/digital-wardrobe/image-1776467798522-ce750eabf7ef2e2c.png.png",
    "price": 434,
    "wearCount": 0
  },
  {
    "name": "Black Shoes",
    "type": "shoes",
    "color": "black",
    "season": "mild",
    "occasion": "casual",
    "gender": "male",
    "imageUrl": "https://res.cloudinary.com/dazn6zthy/image/upload/v1776467899/digital-wardrobe/image-1776467894387-d140d9449fba2d30.png.png",
    "price": 562,
    "wearCount": 0
  },
  {
    "name": "Black Shoes",
    "type": "shoes",
    "color": "black",
    "season": "mild",
    "occasion": "casual",
    "gender": "male",
    "imageUrl": "https://res.cloudinary.com/dazn6zthy/image/upload/v1776538685/digital-wardrobe/image-1776538684341-272cecc5830046d1.png.png",
    "price": 135,
    "wearCount": 0
  }
]